x11x_wagtail_blog/__init__.py
x11x_wagtail_blog/apps.py
x11x_wagtail_blog/fakers.py
x11x_wagtail_blog/models.py
x11x_wagtail_blog/views.py
x11x_wagtail_blog/migrations/0001_initial.py
x11x_wagtail_blog/migrations/__init__.py
x11x_wagtail_blog/templates/x11x_wagtail_blog/about_the_author.html
x11x_wagtail_blog/templates/x11x_wagtail_blog/tests/testing_models/testing_article_page.html
x11x_wagtail_blog/templatetags/__init__.py
x11x_wagtail_blog/templatetags/x11x_wagtail_blog.py
x11x_wagtail_blog/tests/__init__.py
x11x_wagtail_blog/tests/test_docs.py
x11x_wagtail_blog/tests/test_extensible_article_page.py
x11x_wagtail_blog/tests/testing_models/__init__.py
x11x_wagtail_blog/tests/testing_models/apps.py
x11x_wagtail_blog/tests/testing_models/fakers.py
x11x_wagtail_blog/tests/testing_models/models.py
x11x_wagtail_blog/tests/testing_models/migrations/0001_initial.py
x11x_wagtail_blog/tests/testing_models/migrations/__init__.py
11x_wagtail_blog-0.2.0.dist-info/LICENSE
11x_wagtail_blog-0.2.0.dist-info/WHEEL
11x_wagtail_blog-0.2.0.dist-info/METADATA
11x_wagtail_blog-0.2.0.dist-info/RECORD
